shortener/__init__.py
shortener/exceptions.py
shortener/shortener.py
tests/__init__.py
tests/test_shortener.py
django_link_url_shortener-1.0.dist-info/LICENSE
django_link_url_shortener-1.0.dist-info/METADATA
django_link_url_shortener-1.0.dist-info/WHEEL
django_link_url_shortener-1.0.dist-info/top_level.txt
django_link_url_shortener-1.0.dist-info/RECORD
