Metadata-Version: 2.1
Name: django-link-url-shortener
Version: 1.0
Summary: A professional URL shortener utility for Django projects.
Home-page: https://github.com/mrisis/django-url-shortener
Author: Reza Amin
Author-email: rezaamin8889@gmail.com
License: MIT
Platform: UNKNOWN
Classifier: Programming Language :: Python
Classifier: Programming Language :: Python :: 3
Classifier: License :: OSI Approved :: MIT License
License-File: LICENSE
